double_dabble/example/hdl/double_dabble.v
`timescale 1ns / 1ps

module binary2bcd_double_dabble(
	input  [7:0]in_binary,
	output reg [7:0]packed_bcd,
	output reg [15:0]unpacked_bcd
);

reg [15:0]scratch_pad;
integer i;


always @(*)begin
	
	scratch_pad = {8'd0,in_binary};
	
	if(in_binary<8'd100)begin

		for(i = 0; i < 7; i = i + 1)begin
			scratch_pad = scratch_pad << 1;
			if (scratch_pad[11:8] > 4'd4)
				scratch_pad[11:8] = scratch_pad[11:8] + 4'd3;
			else
				scratch_pad = scratch_pad;
		end
		
		scratch_pad = scratch_pad << 1;
	end else begin
			scratch_pad = 16'bZ;			
	end
	
end

always @(*)begin

	packed_bcd = scratch_pad[15:8];
	unpacked_bcd = {4'd0, scratch_pad[15:12], 4'd0, scratch_pad[11:8]};
end

endmodule

double_dabble/example/xsim/testbench.v
// set the timescale for the simulation
 `timescale 1ns/1ps 
module testbench;  // module of testbench
//  parameter defined
parameter CYCLE = 10; // use CYCLE to describe the clock period
parameter LARGE_NUMBER  = 1000;// max cycle time=>timeout

// localparam
//localparam DATA_WIDTH= 16;
localparam N=256;


// input signal use reg
reg clk;
reg rst_n;
reg  [7:0]in_binary;

// output signal use wire
wire  [7:0]packed_bcd;
wire  [15:0]unpacked_bcd;
// interger 
integer i, j, error;
///// instantiate  module /////
// instantiate the module you finished in following format //
// module_name #(.parameter1(5),.parameter2(3)) unit_name (.port1(...), .port2(...), ...); //

    binary2bcd_double_dabble binary2bcd_double_dabble_0(
        .in_binary(in_binary),
        .packed_bcd(packed_bcd),
        .unpacked_bcd(unpacked_bcd)
    );

//  dump the waveform of the simulation for fsdb//
/*initial begin
 $fsdbDumpfile("testbench.fsdb"); 
 $fsdbDumpvars;              
end*/

// dump the waveform of the simulation for vcd//
initial begin
  $dumpfile("testbench.vcd");
  $dumpvars("+mda");
end

// there you can read data from the file,and store in the register.
reg [31:0] golden [0:N];
initial begin
  $readmemb("golden.dat",golden);
end



// generate clk 
always #(CYCLE/2) clk = ~clk; 

// System block set only clock,reset signal and the timeout finish. 
initial begin
  clk = 1;
  rst_n = 1;
  // system reset
  #(CYCLE) rst_n = 0;
  #(CYCLE) rst_n = 1;

  #(CYCLE*LARGE_NUMBER) $finish;
end

// input signal setting, pattern feeding and set control signal blcok.

initial begin
  // 1. set the initial state of the testing signal
  // 2. you can use wait or @(negedge clk), to control when to feed your pattern
  // ex: wait(rst_n==1) do something.../ @(negedge clk) do something...
  // 3. you can use for or while loop to generate all possible inputs to verify your answer
  // ex: for(i=0;i<50;i=i+1)begin   // no i++ in verilog
  // 4. the input data can from external file, or you can generate the pattern in the testbench
  in_binary = 0;
  wait(rst_n==0);
  wait(rst_n==1);

  for(i=0; i<N; i=i+1) begin
    @(negedge clk) in_binary=golden[i][15:8];
  end
end

// output result checking block, control when to sample and verify the result.
integer  fp_w;
initial begin
// error count
  error = 0;
// Use the same control technique to control when to sample output result.
  wait(rst_n==0);
  wait(rst_n==1);
// adder output for two cycle from input to output
  #(CYCLE*1);
  // you can also write the result to a text file
  fp_w = $fopen("answer.txt");
  for(j=0; j<N; j=j+1) begin
    @(negedge clk);
    if(packed_bcd !== golden[j][7:0])begin
      error = error + 1;
      // print the text on the termial by display.
      $display("************* Pattern No.%d is wrong at %t ************", j,$time);
      $display("in_binary = %b, ",golden[j][15:8]);  
      $display("golden = %b, but your answer is %b QQ Orz ",golden[j][7:0], packed_bcd);  
      //$finish;
    end
    // write the text in .txt by fdisplay.
    $fdisplay(fp_w, "%h_%h",golden[j][7:0],packed_bcd);
  end
  $fclose(fp_w); 
  // check the error count
  if(error==0) begin
    $display("Congratulations!! The functionality of your adder is correct!!");
  end
  else begin
    $display("error !!");
  end 
  #(CYCLE) $finish;
end

endmodule

double_dabble/example/xsim/testbench.vcd
$date
   Wed Jan  8 15:11:51 2025
$end
$version
  2022.1
$end
$timescale
  1ps
$end
$scope module testbench $end
$var reg 1 ! clk $end
$var reg 1 " rst_n $end
$var reg 8 # in_binary [7:0] $end
$var wire 8 $ packed_bcd [7:0] $end
$var wire 16 % unpacked_bcd [15:0] $end
$var integer 32 & i [31:0] $end
$var integer 32 ' j [31:0] $end
$var integer 32 ( error [31:0] $end
$var integer 32 ) fp_w [31:0] $end
$scope module binary2bcd_double_dabble_0 $end
$var wire 8 * in_binary [7:0] $end
$var reg 8 + packed_bcd [7:0] $end
$var reg 16 , unpacked_bcd [15:0] $end
$var reg 16 - scratch_pad [15:0] $end
$var integer 32 . i [31:0] $end
$upscope $end
$upscope $end
$enddefinitions $end
#0
$dumpvars
1!
1"
b0 #
b0 $
b0 %
bx &
bx '
b0 (
bx )
b0 *
b0 +
b0 ,
b0 -
b111 .
$end
#5000
0!
#10000
1!
0"
#15000
0!
#20000
1!
1"
b0 &
#25000
0!
b0 #
b1 &
#30000
1!
b0 '
b10 )
#35000
0!
b1 #
b1 $
b1 %
b10 &
b1 '
b1 *
b1 +
b1 ,
b100000000 -
b111 .
#40000
1!
#45000
0!
b10 #
b10 $
b10 %
b11 &
b10 '
b10 *
b10 +
b10 ,
b1000000000 -
b111 .
#50000
1!
#55000
0!
b11 #
b11 $
b11 %
b100 &
b11 '
b11 *
b11 +
b11 ,
b1100000000 -
b111 .
#60000
1!
#65000
0!
b100 #
b100 $
b100 %
b101 &
b100 '
b100 *
b100 +
b100 ,
b10000000000 -
b111 .
#70000
1!
#75000
0!
b101 #
b101 $
b101 %
b110 &
b101 '
b101 *
b101 +
b101 ,
b10100000000 -
b111 .
#80000
1!
#85000
0!
b110 #
b110 $
b110 %
b111 &
b110 '
b110 *
b110 +
b110 ,
b11000000000 -
b111 .
#90000
1!
#95000
0!
b111 #
b111 $
b111 %
b1000 &
b111 '
b111 *
b111 +
b111 ,
b11100000000 -
b111 .
#100000
1!
#105000
0!
b1000 #
b1000 $
b1000 %
b1001 &
b1000 '
b1000 *
b1000 +
b1000 ,
b100000000000 -
b111 .
#110000
1!
#115000
0!
b1001 #
b1001 $
b1001 %
b1010 &
b1001 '
b1001 *
b1001 +
b1001 ,
b100100000000 -
b111 .
#120000
1!
#125000
0!
b1010 #
b10000 $
b100000000 %
b1011 &
b1010 '
b1010 *
b10000 +
b100000000 ,
b1000000000000 -
b111 .
#130000
1!
#135000
0!
b1011 #
b10001 $
b100000001 %
b1100 &
b1011 '
b1011 *
b10001 +
b100000001 ,
b1000100000000 -
b111 .
#140000
1!
#145000
0!
b1100 #
b10010 $
b100000010 %
b1101 &
b1100 '
b1100 *
b10010 +
b100000010 ,
b1001000000000 -
b111 .
#150000
1!
#155000
0!
b1101 #
b10011 $
b100000011 %
b1110 &
b1101 '
b1101 *
b10011 +
b100000011 ,
b1001100000000 -
b111 .
#160000
1!
#165000
0!
b1110 #
b10100 $
b100000100 %
b1111 &
b1110 '
b1110 *
b10100 +
b100000100 ,
b1010000000000 -
b111 .
#170000
1!
#175000
0!
b1111 #
b10101 $
b100000101 %
b10000 &
b1111 '
b1111 *
b10101 +
b100000101 ,
b1010100000000 -
b111 .
#180000
1!
#185000
0!
b10000 #
b10110 $
b100000110 %
b10001 &
b10000 '
b10000 *
b10110 +
b100000110 ,
b1011000000000 -
b111 .
#190000
1!
#195000
0!
b10001 #
b10111 $
b100000111 %
b10010 &
b10001 '
b10001 *
b10111 +
b100000111 ,
b1011100000000 -
b111 .
#200000
1!
#205000
0!
b10010 #
b11000 $
b100001000 %
b10011 &
b10010 '
b10010 *
b11000 +
b100001000 ,
b1100000000000 -
b111 .
#210000
1!
#215000
0!
b10011 #
b11001 $
b100001001 %
b10100 &
b10011 '
b10011 *
b11001 +
b100001001 ,
b1100100000000 -
b111 .
#220000
1!
#225000
0!
b10100 #
b100000 $
b1000000000 %
b10101 &
b10100 '
b10100 *
b100000 +
b1000000000 ,
b10000000000000 -
b111 .
#230000
1!
#235000
0!
b10101 #
b100001 $
b1000000001 %
b10110 &
b10101 '
b10101 *
b100001 +
b1000000001 ,
b10000100000000 -
b111 .
#240000
1!
#245000
0!
b10110 #
b100010 $
b1000000010 %
b10111 &
b10110 '
b10110 *
b100010 +
b1000000010 ,
b10001000000000 -
b111 .
#250000
1!
#255000
0!
b10111 #
b100011 $
b1000000011 %
b11000 &
b10111 '
b10111 *
b100011 +
b1000000011 ,
b10001100000000 -
b111 .
#260000
1!
#265000
0!
b11000 #
b100100 $
b1000000100 %
b11001 &
b11000 '
b11000 *
b100100 +
b1000000100 ,
b10010000000000 -
b111 .
#270000
1!
#275000
0!
b11001 #
b100101 $
b1000000101 %
b11010 &
b11001 '
b11001 *
b100101 +
b1000000101 ,
b10010100000000 -
b111 .
#280000
1!
#285000
0!
b11010 #
b100110 $
b1000000110 %
b11011 &
b11010 '
b11010 *
b100110 +
b1000000110 ,
b10011000000000 -
b111 .
#290000
1!
#295000
0!
b11011 #
b100111 $
b1000000111 %
b11100 &
b11011 '
b11011 *
b100111 +
b1000000111 ,
b10011100000000 -
b111 .
#300000
1!
#305000
0!
b11100 #
b101000 $
b1000001000 %
b11101 &
b11100 '
b11100 *
b101000 +
b1000001000 ,
b10100000000000 -
b111 .
#310000
1!
#315000
0!
b11101 #
b101001 $
b1000001001 %
b11110 &
b11101 '
b11101 *
b101001 +
b1000001001 ,
b10100100000000 -
b111 .
#320000
1!
#325000
0!
b11110 #
b110000 $
b1100000000 %
b11111 &
b11110 '
b11110 *
b110000 +
b1100000000 ,
b11000000000000 -
b111 .
#330000
1!
#335000
0!
b11111 #
b110001 $
b1100000001 %
b100000 &
b11111 '
b11111 *
b110001 +
b1100000001 ,
b11000100000000 -
b111 .
#340000
1!
#345000
0!
b100000 #
b110010 $
b1100000010 %
b100001 &
b100000 '
b100000 *
b110010 +
b1100000010 ,
b11001000000000 -
b111 .
#350000
1!
#355000
0!
b100001 #
b110011 $
b1100000011 %
b100010 &
b100001 '
b100001 *
b110011 +
b1100000011 ,
b11001100000000 -
b111 .
#360000
1!
#365000
0!
b100010 #
b110100 $
b1100000100 %
b100011 &
b100010 '
b100010 *
b110100 +
b1100000100 ,
b11010000000000 -
b111 .
#370000
1!
#375000
0!
b100011 #
b110101 $
b1100000101 %
b100100 &
b100011 '
b100011 *
b110101 +
b1100000101 ,
b11010100000000 -
b111 .
#380000
1!
#385000
0!
b100100 #
b110110 $
b1100000110 %
b100101 &
b100100 '
b100100 *
b110110 +
b1100000110 ,
b11011000000000 -
b111 .
#390000
1!
#395000
0!
b100101 #
b110111 $
b1100000111 %
b100110 &
b100101 '
b100101 *
b110111 +
b1100000111 ,
b11011100000000 -
b111 .
#400000
1!
#405000
0!
b100110 #
b111000 $
b1100001000 %
b100111 &
b100110 '
b100110 *
b111000 +
b1100001000 ,
b11100000000000 -
b111 .
#410000
1!
#415000
0!
b100111 #
b111001 $
b1100001001 %
b101000 &
b100111 '
b100111 *
b111001 +
b1100001001 ,
b11100100000000 -
b111 .
#420000
1!
#425000
0!
b101000 #
b1000000 $
b10000000000 %
b101001 &
b101000 '
b101000 *
b1000000 +
b10000000000 ,
b100000000000000 -
b111 .
#430000
1!
#435000
0!
b101001 #
b1000001 $
b10000000001 %
b101010 &
b101001 '
b101001 *
b1000001 +
b10000000001 ,
b100000100000000 -
b111 .
#440000
1!
#445000
0!
b101010 #
b1000010 $
b10000000010 %
b101011 &
b101010 '
b101010 *
b1000010 +
b10000000010 ,
b100001000000000 -
b111 .
#450000
1!
#455000
0!
b101011 #
b1000011 $
b10000000011 %
b101100 &
b101011 '
b101011 *
b1000011 +
b10000000011 ,
b100001100000000 -
b111 .
#460000
1!
#465000
0!
b101100 #
b1000100 $
b10000000100 %
b101101 &
b101100 '
b101100 *
b1000100 +
b10000000100 ,
b100010000000000 -
b111 .
#470000
1!
#475000
0!
b101101 #
b1000101 $
b10000000101 %
b101110 &
b101101 '
b101101 *
b1000101 +
b10000000101 ,
b100010100000000 -
b111 .
#480000
1!
#485000
0!
b101110 #
b1000110 $
b10000000110 %
b101111 &
b101110 '
b101110 *
b1000110 +
b10000000110 ,
b100011000000000 -
b111 .
#490000
1!
#495000
0!
b101111 #
b1000111 $
b10000000111 %
b110000 &
b101111 '
b101111 *
b1000111 +
b10000000111 ,
b100011100000000 -
b111 .
#500000
1!
#505000
0!
b110000 #
b1001000 $
b10000001000 %
b110001 &
b110000 '
b110000 *
b1001000 +
b10000001000 ,
b100100000000000 -
b111 .
#510000
1!
#515000
0!
b110001 #
b1001001 $
b10000001001 %
b110010 &
b110001 '
b110001 *
b1001001 +
b10000001001 ,
b100100100000000 -
b111 .
#520000
1!
#525000
0!
b110010 #
b1010000 $
b10100000000 %
b110011 &
b110010 '
b110010 *
b1010000 +
b10100000000 ,
b101000000000000 -
b111 .
#530000
1!
#535000
0!
b110011 #
b1010001 $
b10100000001 %
b110100 &
b110011 '
b110011 *
b1010001 +
b10100000001 ,
b101000100000000 -
b111 .
#540000
1!
#545000
0!
b110100 #
b1010010 $
b10100000010 %
b110101 &
b110100 '
b110100 *
b1010010 +
b10100000010 ,
b101001000000000 -
b111 .
#550000
1!
#555000
0!
b110101 #
b1010011 $
b10100000011 %
b110110 &
b110101 '
b110101 *
b1010011 +
b10100000011 ,
b101001100000000 -
b111 .
#560000
1!
#565000
0!
b110110 #
b1010100 $
b10100000100 %
b110111 &
b110110 '
b110110 *
b1010100 +
b10100000100 ,
b101010000000000 -
b111 .
#570000
1!
#575000
0!
b110111 #
b1010101 $
b10100000101 %
b111000 &
b110111 '
b110111 *
b1010101 +
b10100000101 ,
b101010100000000 -
b111 .
#580000
1!
#585000
0!
b111000 #
b1010110 $
b10100000110 %
b111001 &
b111000 '
b111000 *
b1010110 +
b10100000110 ,
b101011000000000 -
b111 .
#590000
1!
#595000
0!
b111001 #
b1010111 $
b10100000111 %
b111010 &
b111001 '
b111001 *
b1010111 +
b10100000111 ,
b101011100000000 -
b111 .
#600000
1!
#605000
0!
b111010 #
b1011000 $
b10100001000 %
b111011 &
b111010 '
b111010 *
b1011000 +
b10100001000 ,
b101100000000000 -
b111 .
#610000
1!
#615000
0!
b111011 #
b1011001 $
b10100001001 %
b111100 &
b111011 '
b111011 *
b1011001 +
b10100001001 ,
b101100100000000 -
b111 .
#620000
1!
#625000
0!
b111100 #
b1100000 $
b11000000000 %
b111101 &
b111100 '
b111100 *
b1100000 +
b11000000000 ,
b110000000000000 -
b111 .
#630000
1!
#635000
0!
b111101 #
b1100001 $
b11000000001 %
b111110 &
b111101 '
b111101 *
b1100001 +
b11000000001 ,
b110000100000000 -
b111 .
#640000
1!
#645000
0!
b111110 #
b1100010 $
b11000000010 %
b111111 &
b111110 '
b111110 *
b1100010 +
b11000000010 ,
b110001000000000 -
b111 .
#650000
1!
#655000
0!
b111111 #
b1100011 $
b11000000011 %
b1000000 &
b111111 '
b111111 *
b1100011 +
b11000000011 ,
b110001100000000 -
b111 .
#660000
1!
#665000
0!
b1000000 #
b1100100 $
b11000000100 %
b1000001 &
b1000000 '
b1000000 *
b1100100 +
b11000000100 ,
b110010000000000 -
b111 .
#670000
1!
#675000
0!
b1000001 #
b1100101 $
b11000000101 %
b1000010 &
b1000001 '
b1000001 *
b1100101 +
b11000000101 ,
b110010100000000 -
b111 .
#680000
1!
#685000
0!
b1000010 #
b1100110 $
b11000000110 %
b1000011 &
b1000010 '
b1000010 *
b1100110 +
b11000000110 ,
b110011000000000 -
b111 .
#690000
1!
#695000
0!
b1000011 #
b1100111 $
b11000000111 %
b1000100 &
b1000011 '
b1000011 *
b1100111 +
b11000000111 ,
b110011100000000 -
b111 .
#700000
1!
#705000
0!
b1000100 #
b1101000 $
b11000001000 %
b1000101 &
b1000100 '
b1000100 *
b1101000 +
b11000001000 ,
b110100000000000 -
b111 .
#710000
1!
#715000
0!
b1000101 #
b1101001 $
b11000001001 %
b1000110 &
b1000101 '
b1000101 *
b1101001 +
b11000001001 ,
b110100100000000 -
b111 .
#720000
1!
#725000
0!
b1000110 #
b1110000 $
b11100000000 %
b1000111 &
b1000110 '
b1000110 *
b1110000 +
b11100000000 ,
b111000000000000 -
b111 .
#730000
1!
#735000
0!
b1000111 #
b1110001 $
b11100000001 %
b1001000 &
b1000111 '
b1000111 *
b1110001 +
b11100000001 ,
b111000100000000 -
b111 .
#740000
1!
#745000
0!
b1001000 #
b1110010 $
b11100000010 %
b1001001 &
b1001000 '
b1001000 *
b1110010 +
b11100000010 ,
b111001000000000 -
b111 .
#750000
1!
#755000
0!
b1001001 #
b1110011 $
b11100000011 %
b1001010 &
b1001001 '
b1001001 *
b1110011 +
b11100000011 ,
b111001100000000 -
b111 .
#760000
1!
#765000
0!
b1001010 #
b1110100 $
b11100000100 %
b1001011 &
b1001010 '
b1001010 *
b1110100 +
b11100000100 ,
b111010000000000 -
b111 .
#770000
1!
#775000
0!
b1001011 #
b1110101 $
b11100000101 %
b1001100 &
b1001011 '
b1001011 *
b1110101 +
b11100000101 ,
b111010100000000 -
b111 .
#780000
1!
#785000
0!
b1001100 #
b1110110 $
b11100000110 %
b1001101 &
b1001100 '
b1001100 *
b1110110 +
b11100000110 ,
b111011000000000 -
b111 .
#790000
1!
#795000
0!
b1001101 #
b1110111 $
b11100000111 %
b1001110 &
b1001101 '
b1001101 *
b1110111 +
b11100000111 ,
b111011100000000 -
b111 .
#800000
1!
#805000
0!
b1001110 #
b1111000 $
b11100001000 %
b1001111 &
b1001110 '
b1001110 *
b1111000 +
b11100001000 ,
b111100000000000 -
b111 .
#810000
1!
#815000
0!
b1001111 #
b1111001 $
b11100001001 %
b1010000 &
b1001111 '
b1001111 *
b1111001 +
b11100001001 ,
b111100100000000 -
b111 .
#820000
1!
#825000
0!
b1010000 #
b10000000 $
b100000000000 %
b1010001 &
b1010000 '
b1010000 *
b10000000 +
b100000000000 ,
b1000000000000000 -
b111 .
#830000
1!
#835000
0!
b1010001 #
b10000001 $
b100000000001 %
b1010010 &
b1010001 '
b1010001 *
b10000001 +
b100000000001 ,
b1000000100000000 -
b111 .
#840000
1!
#845000
0!
b1010010 #
b10000010 $
b100000000010 %
b1010011 &
b1010010 '
b1010010 *
b10000010 +
b100000000010 ,
b1000001000000000 -
b111 .
#850000
1!
#855000
0!
b1010011 #
b10000011 $
b100000000011 %
b1010100 &
b1010011 '
b1010011 *
b10000011 +
b100000000011 ,
b1000001100000000 -
b111 .
#860000
1!
#865000
0!
b1010100 #
b10000100 $
b100000000100 %
b1010101 &
b1010100 '
b1010100 *
b10000100 +
b100000000100 ,
b1000010000000000 -
b111 .
#870000
1!
#875000
0!
b1010101 #
b10000101 $
b100000000101 %
b1010110 &
b1010101 '
b1010101 *
b10000101 +
b100000000101 ,
b1000010100000000 -
b111 .
#880000
1!
#885000
0!
b1010110 #
b10000110 $
b100000000110 %
b1010111 &
b1010110 '
b1010110 *
b10000110 +
b100000000110 ,
b1000011000000000 -
b111 .
#890000
1!
#895000
0!
b1010111 #
b10000111 $
b100000000111 %
b1011000 &
b1010111 '
b1010111 *
b10000111 +
b100000000111 ,
b1000011100000000 -
b111 .
#900000
1!
#905000
0!
b1011000 #
b10001000 $
b100000001000 %
b1011001 &
b1011000 '
b1011000 *
b10001000 +
b100000001000 ,
b1000100000000000 -
b111 .
#910000
1!
#915000
0!
b1011001 #
b10001001 $
b100000001001 %
b1011010 &
b1011001 '
b1011001 *
b10001001 +
b100000001001 ,
b1000100100000000 -
b111 .
#920000
1!
#925000
0!
b1011010 #
b10010000 $
b100100000000 %
b1011011 &
b1011010 '
b1011010 *
b10010000 +
b100100000000 ,
b1001000000000000 -
b111 .
#930000
1!
#935000
0!
b1011011 #
b10010001 $
b100100000001 %
b1011100 &
b1011011 '
b1011011 *
b10010001 +
b100100000001 ,
b1001000100000000 -
b111 .
#940000
1!
#945000
0!
b1011100 #
b10010010 $
b100100000010 %
b1011101 &
b1011100 '
b1011100 *
b10010010 +
b100100000010 ,
b1001001000000000 -
b111 .
#950000
1!
#955000
0!
b1011101 #
b10010011 $
b100100000011 %
b1011110 &
b1011101 '
b1011101 *
b10010011 +
b100100000011 ,
b1001001100000000 -
b111 .
#960000
1!
#965000
0!
b1011110 #
b10010100 $
b100100000100 %
b1011111 &
b1011110 '
b1011110 *
b10010100 +
b100100000100 ,
b1001010000000000 -
b111 .
#970000
1!
#975000
0!
b1011111 #
b10010101 $
b100100000101 %
b1100000 &
b1011111 '
b1011111 *
b10010101 +
b100100000101 ,
b1001010100000000 -
b111 .
#980000
1!
#985000
0!
b1100000 #
b10010110 $
b100100000110 %
b1100001 &
b1100000 '
b1100000 *
b10010110 +
b100100000110 ,
b1001011000000000 -
b111 .
#990000
1!
#995000
0!
b1100001 #
b10010111 $
b100100000111 %
b1100010 &
b1100001 '
b1100001 *
b10010111 +
b100100000111 ,
b1001011100000000 -
b111 .
#1000000
1!
#1005000
0!
b1100010 #
b10011000 $
b100100001000 %
b1100011 &
b1100010 '
b1100010 *
b10011000 +
b100100001000 ,
b1001100000000000 -
b111 .
#1010000
1!
#1015000
0!
b1100011 #
b10011001 $
b100100001001 %
b1100100 &
b1100011 '
b1100011 *
b10011001 +
b100100001001 ,
b1001100100000000 -
b111 .
#1020000
1!
#1025000
0!
b1100100 #
bz $
b0zzzz0000zzzz %
b1100101 &
b1100100 '
b1100100 *
bz +
b0zzzz0000zzzz ,
bz -
#1030000
1!
#1035000
0!
b1100101 #
b1100110 &
b1100101 '
b1100101 *
bz +
b0zzzz0000zzzz ,
bz -
#1040000
1!
#1045000
0!
b1100110 #
b1100111 &
b1100110 '
b1100110 *
bz +
b0zzzz0000zzzz ,
bz -
#1050000
1!
#1055000
0!
b1100111 #
b1101000 &
b1100111 '
b1100111 *
bz +
b0zzzz0000zzzz ,
bz -
#1060000
1!
#1065000
0!
b1101000 #
b1101001 &
b1101000 '
b1101000 *
bz +
b0zzzz0000zzzz ,
bz -
#1070000
1!
#1075000
0!
b1101001 #
b1101010 &
b1101001 '
b1101001 *
bz +
b0zzzz0000zzzz ,
bz -
#1080000
1!
#1085000
0!
b1101010 #
b1101011 &
b1101010 '
b1101010 *
bz +
b0zzzz0000zzzz ,
bz -
#1090000
1!
#1095000
0!
b1101011 #
b1101100 &
b1101011 '
b1101011 *
bz +
b0zzzz0000zzzz ,
bz -
#1100000
1!
#1105000
0!
b1101100 #
b1101101 &
b1101100 '
b1101100 *
bz +
b0zzzz0000zzzz ,
bz -
#1110000
1!
#1115000
0!
b1101101 #
b1101110 &
b1101101 '
b1101101 *
bz +
b0zzzz0000zzzz ,
bz -
#1120000
1!
#1125000
0!
b1101110 #
b1101111 &
b1101110 '
b1101110 *
bz +
b0zzzz0000zzzz ,
bz -
#1130000
1!
#1135000
0!
b1101111 #
b1110000 &
b1101111 '
b1101111 *
bz +
b0zzzz0000zzzz ,
bz -
#1140000
1!
#1145000
0!
b1110000 #
b1110001 &
b1110000 '
b1110000 *
bz +
b0zzzz0000zzzz ,
bz -
#1150000
1!
#1155000
0!
b1110001 #
b1110010 &
b1110001 '
b1110001 *
bz +
b0zzzz0000zzzz ,
bz -
#1160000
1!
#1165000
0!
b1110010 #
b1110011 &
b1110010 '
b1110010 *
bz +
b0zzzz0000zzzz ,
bz -
#1170000
1!
#1175000
0!
b1110011 #
b1110100 &
b1110011 '
b1110011 *
bz +
b0zzzz0000zzzz ,
bz -
#1180000
1!
#1185000
0!
b1110100 #
b1110101 &
b1110100 '
b1110100 *
bz +
b0zzzz0000zzzz ,
bz -
#1190000
1!
#1195000
0!
b1110101 #
b1110110 &
b1110101 '
b1110101 *
bz +
b0zzzz0000zzzz ,
bz -
#1200000
1!
#1205000
0!
b1110110 #
b1110111 &
b1110110 '
b1110110 *
bz +
b0zzzz0000zzzz ,
bz -
#1210000
1!
#1215000
0!
b1110111 #
b1111000 &
b1110111 '
b1110111 *
bz +
b0zzzz0000zzzz ,
bz -
#1220000
1!
#1225000
0!
b1111000 #
b1111001 &
b1111000 '
b1111000 *
bz +
b0zzzz0000zzzz ,
bz -
#1230000
1!
#1235000
0!
b1111001 #
b1111010 &
b1111001 '
b1111001 *
bz +
b0zzzz0000zzzz ,
bz -
#1240000
1!
#1245000
0!
b1111010 #
b1111011 &
b1111010 '
b1111010 *
bz +
b0zzzz0000zzzz ,
bz -
#1250000
1!
#1255000
0!
b1111011 #
b1111100 &
b1111011 '
b1111011 *
bz +
b0zzzz0000zzzz ,
bz -
#1260000
1!
#1265000
0!
b1111100 #
b1111101 &
b1111100 '
b1111100 *
bz +
b0zzzz0000zzzz ,
bz -
#1270000
1!
#1275000
0!
b1111101 #
b1111110 &
b1111101 '
b1111101 *
bz +
b0zzzz0000zzzz ,
bz -
#1280000
1!
#1285000
0!
b1111110 #
b1111111 &
b1111110 '
b1111110 *
bz +
b0zzzz0000zzzz ,
bz -
#1290000
1!
#1295000
0!
b1111111 #
b10000000 &
b1111111 '
b1111111 *
bz +
b0zzzz0000zzzz ,
bz -
#1300000
1!
#1305000
0!
b10000000 #
b10000001 &
b10000000 '
b10000000 *
bz +
b0zzzz0000zzzz ,
bz -
#1310000
1!
#1315000
0!
b10000001 #
b10000010 &
b10000001 '
b10000001 *
bz +
b0zzzz0000zzzz ,
bz -
#1320000
1!
#1325000
0!
b10000010 #
b10000011 &
b10000010 '
b10000010 *
bz +
b0zzzz0000zzzz ,
bz -
#1330000
1!
#1335000
0!
b10000011 #
b10000100 &
b10000011 '
b10000011 *
bz +
b0zzzz0000zzzz ,
bz -
#1340000
1!
#1345000
0!
b10000100 #
b10000101 &
b10000100 '
b10000100 *
bz +
b0zzzz0000zzzz ,
bz -
#1350000
1!
#1355000
0!
b10000101 #
b10000110 &
b10000101 '
b10000101 *
bz +
b0zzzz0000zzzz ,
bz -
#1360000
1!
#1365000
0!
b10000110 #
b10000111 &
b10000110 '
b10000110 *
bz +
b0zzzz0000zzzz ,
bz -
#1370000
1!
#1375000
0!
b10000111 #
b10001000 &
b10000111 '
b10000111 *
bz +
b0zzzz0000zzzz ,
bz -
#1380000
1!
#1385000
0!
b10001000 #
b10001001 &
b10001000 '
b10001000 *
bz +
b0zzzz0000zzzz ,
bz -
#1390000
1!
#1395000
0!
b10001001 #
b10001010 &
b10001001 '
b10001001 *
bz +
b0zzzz0000zzzz ,
bz -
#1400000
1!
#1405000
0!
b10001010 #
b10001011 &
b10001010 '
b10001010 *
bz +
b0zzzz0000zzzz ,
bz -
#1410000
1!
#1415000
0!
b10001011 #
b10001100 &
b10001011 '
b10001011 *
bz +
b0zzzz0000zzzz ,
bz -
#1420000
1!
#1425000
0!
b10001100 #
b10001101 &
b10001100 '
b10001100 *
bz +
b0zzzz0000zzzz ,
bz -
#1430000
1!
#1435000
0!
b10001101 #
b10001110 &
b10001101 '
b10001101 *
bz +
b0zzzz0000zzzz ,
bz -
#1440000
1!
#1445000
0!
b10001110 #
b10001111 &
b10001110 '
b10001110 *
bz +
b0zzzz0000zzzz ,
bz -
#1450000
1!
#1455000
0!
b10001111 #
b10010000 &
b10001111 '
b10001111 *
bz +
b0zzzz0000zzzz ,
bz -
#1460000
1!
#1465000
0!
b10010000 #
b10010001 &
b10010000 '
b10010000 *
bz +
b0zzzz0000zzzz ,
bz -
#1470000
1!
#1475000
0!
b10010001 #
b10010010 &
b10010001 '
b10010001 *
bz +
b0zzzz0000zzzz ,
bz -
#1480000
1!
#1485000
0!
b10010010 #
b10010011 &
b10010010 '
b10010010 *
bz +
b0zzzz0000zzzz ,
bz -
#1490000
1!
#1495000
0!
b10010011 #
b10010100 &
b10010011 '
b10010011 *
bz +
b0zzzz0000zzzz ,
bz -
#1500000
1!
#1505000
0!
b10010100 #
b10010101 &
b10010100 '
b10010100 *
bz +
b0zzzz0000zzzz ,
bz -
#1510000
1!
#1515000
0!
b10010101 #
b10010110 &
b10010101 '
b10010101 *
bz +
b0zzzz0000zzzz ,
bz -
#1520000
1!
#1525000
0!
b10010110 #
b10010111 &
b10010110 '
b10010110 *
bz +
b0zzzz0000zzzz ,
bz -
#1530000
1!
#1535000
0!
b10010111 #
b10011000 &
b10010111 '
b10010111 *
bz +
b0zzzz0000zzzz ,
bz -
#1540000
1!
#1545000
0!
b10011000 #
b10011001 &
b10011000 '
b10011000 *
bz +
b0zzzz0000zzzz ,
bz -
#1550000
1!
#1555000
0!
b10011001 #
b10011010 &
b10011001 '
b10011001 *
bz +
b0zzzz0000zzzz ,
bz -
#1560000
1!
#1565000
0!
b10011010 #
b10011011 &
b10011010 '
b10011010 *
bz +
b0zzzz0000zzzz ,
bz -
#1570000
1!
#1575000
0!
b10011011 #
b10011100 &
b10011011 '
b10011011 *
bz +
b0zzzz0000zzzz ,
bz -
#1580000
1!
#1585000
0!
b10011100 #
b10011101 &
b10011100 '
b10011100 *
bz +
b0zzzz0000zzzz ,
bz -
#1590000
1!
#1595000
0!
b10011101 #
b10011110 &
b10011101 '
b10011101 *
bz +
b0zzzz0000zzzz ,
bz -
#1600000
1!
#1605000
0!
b10011110 #
b10011111 &
b10011110 '
b10011110 *
bz +
b0zzzz0000zzzz ,
bz -
#1610000
1!
#1615000
0!
b10011111 #
b10100000 &
b10011111 '
b10011111 *
bz +
b0zzzz0000zzzz ,
bz -
#1620000
1!
#1625000
0!
b10100000 #
b10100001 &
b10100000 '
b10100000 *
bz +
b0zzzz0000zzzz ,
bz -
#1630000
1!
#1635000
0!
b10100001 #
b10100010 &
b10100001 '
b10100001 *
bz +
b0zzzz0000zzzz ,
bz -
#1640000
1!
#1645000
0!
b10100010 #
b10100011 &
b10100010 '
b10100010 *
bz +
b0zzzz0000zzzz ,
bz -
#1650000
1!
#1655000
0!
b10100011 #
b10100100 &
b10100011 '
b10100011 *
bz +
b0zzzz0000zzzz ,
bz -
#1660000
1!
